tocantins_framework/__init__.py
tocantins_framework/anomaly_detection.py
tocantins_framework/calculator.py
tocantins_framework/io.py
tocantins_framework/metrics.py
tocantins_framework/morphology.py
tocantins_framework/preprocessing.py
tocantins_framework/py.typed
tocantins_framework-1.1.0.dist-info/licenses/LICENSE
tocantins_framework-1.1.0.dist-info/METADATA
tocantins_framework-1.1.0.dist-info/WHEEL
tocantins_framework-1.1.0.dist-info/top_level.txt
tocantins_framework-1.1.0.dist-info/RECORD
