Metadata-Version: 2.4
Name: tocantins-framework
Version: 1.1.0
Summary: A comprehensive framework for detecting and quantifying intra-urban thermal anomalies in Landsat imagery using machine learning and spatial analysis
Author-email: Isaque Carvalho Borges <isaque@ecoacaobrasil.org>
Maintainer-email: EcoAção Brasil <isaque@ecoacaobrasil.org>
License: MIT
Project-URL: Homepage, https://github.com/EcoAcao-Brasil/tocantins-framework
Project-URL: Repository, https://github.com/EcoAcao-Brasil/tocantins-framework.git
Project-URL: Changelog, https://github.com/EcoAcao-Brasil/Tocantins-Framework/blob/main/CHANGELOG.md
Keywords: urban heat island,thermal anomaly detection,landsat,remote sensing,machine learning,spatial analysis,climate adaptation,urban planning,environmental monitoring
Classifier: Development Status :: 4 - Beta
Classifier: Intended Audience :: Science/Research
Classifier: Intended Audience :: Developers
Classifier: Topic :: Scientific/Engineering :: GIS
Classifier: Topic :: Scientific/Engineering :: Atmospheric Science
Classifier: Topic :: Scientific/Engineering :: Image Processing
Classifier: License :: OSI Approved :: MIT License
Classifier: Programming Language :: Python :: 3
Classifier: Programming Language :: Python :: 3.8
Classifier: Programming Language :: Python :: 3.9
Classifier: Programming Language :: Python :: 3.10
Classifier: Programming Language :: Python :: 3.11
Classifier: Programming Language :: Python :: 3.12
Classifier: Operating System :: OS Independent
Classifier: Natural Language :: English
Requires-Python: >=3.8
License-File: LICENSE
Requires-Dist: numpy>=1.21.0
Requires-Dist: pandas>=1.3.0
Requires-Dist: rasterio>=1.2.0
Requires-Dist: scikit-learn>=1.0.0
Requires-Dist: scikit-image>=0.18.0
Requires-Dist: scipy>=1.7.0
Provides-Extra: dev
Requires-Dist: pytest>=7.0.0; extra == "dev"
Requires-Dist: pytest-cov>=3.0.0; extra == "dev"
Requires-Dist: black>=22.0.0; extra == "dev"
Requires-Dist: flake8>=4.0.0; extra == "dev"
Requires-Dist: mypy>=0.950; extra == "dev"
Requires-Dist: isort>=5.10.0; extra == "dev"
Requires-Dist: pre-commit>=2.17.0; extra == "dev"
Provides-Extra: docs
Requires-Dist: sphinx>=4.5.0; extra == "docs"
Requires-Dist: sphinx-rtd-theme>=1.0.0; extra == "docs"
Requires-Dist: sphinxcontrib-napoleon>=0.7; extra == "docs"
Provides-Extra: viz
Requires-Dist: matplotlib>=3.5.0; extra == "viz"
Requires-Dist: seaborn>=0.11.0; extra == "viz"
Provides-Extra: all
Requires-Dist: tocantins-framework[dev,docs,viz]; extra == "all"
Dynamic: license-file
